leve/__init__.py
leve/main.py
leve/py.typed
leve/utils.py
leve-0.1.2.dist-info/METADATA
leve-0.1.2.dist-info/WHEEL
leve-0.1.2.dist-info/licenses/LICENSE
leve-0.1.2.dist-info/RECORD
