Metadata-Version: 2.4
Name: leve
Version: 0.1.2
Summary: A python library written in pure python, without any extra dependency to work with string matching algorithms
Project-URL: Homepage, https://github.com/kemphire/leve
Project-URL: Repository, https://github.com/kemphire/leve
Project-URL: Issues, https://github.com/kemphire/leve/issues
Author-email: kartikey Shahi <kartikeyshahi@hotmail.com>
License: MIT License
License-File: LICENSE
Keywords: levenshtein,nlp,string matching
Classifier: License :: OSI Approved :: MIT License
Classifier: Operating System :: OS Independent
Classifier: Programming Language :: Python :: 3
Requires-Python: >=3.10
